pycsound/__init__.py
pycsound/exceptions.py
pycsound/perf_graph.py
pycsound/pycsound.py
PyCsound-1.1.0.dist-info/LICENSE.txt
PyCsound-1.1.0.dist-info/METADATA
PyCsound-1.1.0.dist-info/WHEEL
PyCsound-1.1.0.dist-info/top_level.txt
PyCsound-1.1.0.dist-info/RECORD
