Metadata-Version: 2.1
Name: PyCsound
Version: 1.1.0
Summary: Working with Csound in Python...
Author: Pasquale Mainolfi
Author-email: <mnlpql@gmail.com>
Keywords: csound,sound,sound synthesis,python
Classifier: Programming Language :: Python :: 3
Classifier: Operating System :: Unix
Classifier: Operating System :: MacOS :: MacOS X
Classifier: Operating System :: Microsoft :: Windows
Classifier: License :: OSI Approved :: MIT License
License-File: LICENSE.txt
Requires-Dist: numpy
Requires-Dist: matplotlib
